{
  "type": "server.cardspackage.Minions.LeperGnome",
  "data": {
    "HP": 1,
    "attack": 1,
    "usedToAttack": false,
    "windfury": false,
    "taunt": false,
    "divineShield": false,
    "deathrattle": true,
    "battlecry": false,
    "rush": false,
    "quest": false,
    "mana": 1,
    "name": "Leper Gnome",
    "use": 0,
    "rarity": "common",
    "cardClass": "Neutral",
    "description": "Deathrattle: Deal 2 damage to the enemy hero.",
    "type": "Minion",
    "needTarget": true
  }
}